jax_control_algorithms/__init__.py
jax_control_algorithms/common.py
jax_control_algorithms/estimation.py
jax_control_algorithms/jax_helper.py
jax_control_algorithms/plot_helpers.py
jax_control_algorithms/sysident.py
jax_control_algorithms/trajectory_optimization.py
jax_control_algorithms/ui.py
jax_control_algorithms/trajectory_optim/boundary_function.py
jax_control_algorithms/trajectory_optim/cost_function.py
jax_control_algorithms/trajectory_optim/dynamics_constraints.py
jax_control_algorithms/trajectory_optim/outer_loop_solver.py
jax_control_algorithms/trajectory_optim/penality_method.py
jax_control_algorithms/trajectory_optim/problem_definition.py
jax_control_algorithms-0.6.3.dist-info/LICENSE
jax_control_algorithms-0.6.3.dist-info/METADATA
jax_control_algorithms-0.6.3.dist-info/WHEEL
jax_control_algorithms-0.6.3.dist-info/top_level.txt
jax_control_algorithms-0.6.3.dist-info/RECORD
