Metadata-Version: 2.1
Name: jax_control_algorithms
Version: 0.6.3
Summary: Algorithms for state estimation, control, and system identification in JAX
Author-email: Christian Klauer <chr.klauer@gmail.com>
Project-URL: Homepage, https://github.com/christianausb/controlAlgorithms
Classifier: Programming Language :: Python :: 3
Classifier: License :: OSI Approved :: MIT License
Classifier: Operating System :: OS Independent
Requires-Python: >=3.7
License-File: LICENSE
Requires-Dist: numpy
Requires-Dist: pandas
Requires-Dist: jax
Requires-Dist: jaxopt
Requires-Dist: plotly
Requires-Dist: matplotlib
Requires-Dist: ipywidgets
